tap_tiktok_business/__init__.py
tap_tiktok_business/auth.py
tap_tiktok_business/client.py
tap_tiktok_business/schemas/accounts.schema.json
tap_tiktok_business/schemas/comments.schema.json
tap_tiktok_business/schemas/videos.schema.json
tap_tiktok_business/streams.py
tap_tiktok_business/tap.py
tap_tiktok_business/tests/__init__.py
tap_tiktok_business/tests/test_core.py
tap_tiktok_business-0.0.1.dist-info/entry_points.txt
tap_tiktok_business-0.0.1.dist-info/LICENSE.md
tap_tiktok_business-0.0.1.dist-info/WHEEL
tap_tiktok_business-0.0.1.dist-info/METADATA
tap_tiktok_business-0.0.1.dist-info/RECORD
